{
  "_format": "hh-sol-cache-2",
  "files": {
    "/Users/anjihwan/블벨/BusinessCard/contracts/ERC721Enumerable.sol": {
      "lastModificationDate": 1680085625159,
      "contentHash": "3ecdd77017ebee99b4c174d0f479a628",
      "sourceName": "contracts/ERC721Enumerable.sol",
      "solcConfig": {
        "version": "0.8.7",
        "settings": {
          "optimizer": {
            "enabled": false,
            "runs": 200
          },
          "outputSelection": {
            "*": {
              "*": [
                "abi",
                "evm.bytecode",
                "evm.deployedBytecode",
                "evm.methodIdentifiers",
                "metadata",
                "devdoc",
                "userdoc",
                "storageLayout",
                "evm.gasEstimates"
              ],
              "": [
                "ast"
              ]
            }
          },
          "metadata": {
            "useLiteralContent": true
          }
        }
      },
      "imports": [
        "./ERC721.sol",
        "./extensions/IERC721Enumerable.sol"
      ],
      "versionPragmas": [
        "^0.8.0"
      ],
      "artifacts": [
        "ERC721Enumerable"
      ]
    },
    "/Users/anjihwan/블벨/BusinessCard/contracts/ERC721.sol": {
      "lastModificationDate": 1680085673221,
      "contentHash": "128bd3824bf6c6c75d23ab7d6da69e71",
      "sourceName": "contracts/ERC721.sol",
      "solcConfig": {
        "version": "0.8.7",
        "settings": {
          "optimizer": {
            "enabled": false,
            "runs": 200
          },
          "outputSelection": {
            "*": {
              "*": [
                "abi",
                "evm.bytecode",
                "evm.deployedBytecode",
                "evm.methodIdentifiers",
                "metadata",
                "devdoc",
                "userdoc",
                "storageLayout",
                "evm.gasEstimates"
              ],
              "": [
                "ast"
              ]
            }
          },
          "metadata": {
            "useLiteralContent": true
          }
        }
      },
      "imports": [
        "./IERC721.sol",
        "./IERC721Receiver.sol",
        "./extensions/IERC721Metadata.sol",
        "./utils/Address.sol",
        "./utils/Context.sol",
        "./utils/Strings.sol",
        "./utils/introspection/ERC165.sol"
      ],
      "versionPragmas": [
        "^0.8.0"
      ],
      "artifacts": [
        "ERC721"
      ]
    },
    "/Users/anjihwan/블벨/BusinessCard/contracts/extensions/IERC721Enumerable.sol": {
      "lastModificationDate": 1680085618345,
      "contentHash": "7fefe31862cd6dab8b331986b1b74a61",
      "sourceName": "contracts/extensions/IERC721Enumerable.sol",
      "solcConfig": {
        "version": "0.8.7",
        "settings": {
          "optimizer": {
            "enabled": false,
            "runs": 200
          },
          "outputSelection": {
            "*": {
              "*": [
                "abi",
                "evm.bytecode",
                "evm.deployedBytecode",
                "evm.methodIdentifiers",
                "metadata",
                "devdoc",
                "userdoc",
                "storageLayout",
                "evm.gasEstimates"
              ],
              "": [
                "ast"
              ]
            }
          },
          "metadata": {
            "useLiteralContent": true
          }
        }
      },
      "imports": [
        "../IERC721.sol"
      ],
      "versionPragmas": [
        "^0.8.0"
      ],
      "artifacts": [
        "IERC721Enumerable"
      ]
    },
    "/Users/anjihwan/블벨/BusinessCard/contracts/IERC721.sol": {
      "lastModificationDate": 1680085599245,
      "contentHash": "13fdb65b9baef2543c59e5146c8ce487",
      "sourceName": "contracts/IERC721.sol",
      "solcConfig": {
        "version": "0.8.7",
        "settings": {
          "optimizer": {
            "enabled": false,
            "runs": 200
          },
          "outputSelection": {
            "*": {
              "*": [
                "abi",
                "evm.bytecode",
                "evm.deployedBytecode",
                "evm.methodIdentifiers",
                "metadata",
                "devdoc",
                "userdoc",
                "storageLayout",
                "evm.gasEstimates"
              ],
              "": [
                "ast"
              ]
            }
          },
          "metadata": {
            "useLiteralContent": true
          }
        }
      },
      "imports": [
        "./utils/introspection/IERC165.sol"
      ],
      "versionPragmas": [
        "^0.8.0"
      ],
      "artifacts": [
        "IERC721"
      ]
    },
    "/Users/anjihwan/블벨/BusinessCard/contracts/IERC721Receiver.sol": {
      "lastModificationDate": 1680085668584,
      "contentHash": "c22d4395e33763de693fd440c6fd10e1",
      "sourceName": "contracts/IERC721Receiver.sol",
      "solcConfig": {
        "version": "0.8.7",
        "settings": {
          "optimizer": {
            "enabled": false,
            "runs": 200
          },
          "outputSelection": {
            "*": {
              "*": [
                "abi",
                "evm.bytecode",
                "evm.deployedBytecode",
                "evm.methodIdentifiers",
                "metadata",
                "devdoc",
                "userdoc",
                "storageLayout",
                "evm.gasEstimates"
              ],
              "": [
                "ast"
              ]
            }
          },
          "metadata": {
            "useLiteralContent": true
          }
        }
      },
      "imports": [],
      "versionPragmas": [
        "^0.8.0"
      ],
      "artifacts": [
        "IERC721Receiver"
      ]
    },
    "/Users/anjihwan/블벨/BusinessCard/contracts/extensions/IERC721Metadata.sol": {
      "lastModificationDate": 1680085618345,
      "contentHash": "efbc0d15b80a74e34dbe8da0f3e879bb",
      "sourceName": "contracts/extensions/IERC721Metadata.sol",
      "solcConfig": {
        "version": "0.8.7",
        "settings": {
          "optimizer": {
            "enabled": false,
            "runs": 200
          },
          "outputSelection": {
            "*": {
              "*": [
                "abi",
                "evm.bytecode",
                "evm.deployedBytecode",
                "evm.methodIdentifiers",
                "metadata",
                "devdoc",
                "userdoc",
                "storageLayout",
                "evm.gasEstimates"
              ],
              "": [
                "ast"
              ]
            }
          },
          "metadata": {
            "useLiteralContent": true
          }
        }
      },
      "imports": [
        "../IERC721.sol"
      ],
      "versionPragmas": [
        "^0.8.0"
      ],
      "artifacts": [
        "IERC721Metadata"
      ]
    },
    "/Users/anjihwan/블벨/BusinessCard/contracts/utils/Address.sol": {
      "lastModificationDate": 1680085576149,
      "contentHash": "adb9f6d292b811f18d9db4af963dc06e",
      "sourceName": "contracts/utils/Address.sol",
      "solcConfig": {
        "version": "0.8.7",
        "settings": {
          "optimizer": {
            "enabled": false,
            "runs": 200
          },
          "outputSelection": {
            "*": {
              "*": [
                "abi",
                "evm.bytecode",
                "evm.deployedBytecode",
                "evm.methodIdentifiers",
                "metadata",
                "devdoc",
                "userdoc",
                "storageLayout",
                "evm.gasEstimates"
              ],
              "": [
                "ast"
              ]
            }
          },
          "metadata": {
            "useLiteralContent": true
          }
        }
      },
      "imports": [],
      "versionPragmas": [
        "^0.8.1"
      ],
      "artifacts": [
        "Address"
      ]
    },
    "/Users/anjihwan/블벨/BusinessCard/contracts/utils/Context.sol": {
      "lastModificationDate": 1680085576150,
      "contentHash": "5f2c5c4b6af2dd4551027144797bc8be",
      "sourceName": "contracts/utils/Context.sol",
      "solcConfig": {
        "version": "0.8.7",
        "settings": {
          "optimizer": {
            "enabled": false,
            "runs": 200
          },
          "outputSelection": {
            "*": {
              "*": [
                "abi",
                "evm.bytecode",
                "evm.deployedBytecode",
                "evm.methodIdentifiers",
                "metadata",
                "devdoc",
                "userdoc",
                "storageLayout",
                "evm.gasEstimates"
              ],
              "": [
                "ast"
              ]
            }
          },
          "metadata": {
            "useLiteralContent": true
          }
        }
      },
      "imports": [],
      "versionPragmas": [
        "^0.8.0"
      ],
      "artifacts": [
        "Context"
      ]
    },
    "/Users/anjihwan/블벨/BusinessCard/contracts/utils/Strings.sol": {
      "lastModificationDate": 1680085576151,
      "contentHash": "64daba318ca40b62eb0691a65bad07de",
      "sourceName": "contracts/utils/Strings.sol",
      "solcConfig": {
        "version": "0.8.7",
        "settings": {
          "optimizer": {
            "enabled": false,
            "runs": 200
          },
          "outputSelection": {
            "*": {
              "*": [
                "abi",
                "evm.bytecode",
                "evm.deployedBytecode",
                "evm.methodIdentifiers",
                "metadata",
                "devdoc",
                "userdoc",
                "storageLayout",
                "evm.gasEstimates"
              ],
              "": [
                "ast"
              ]
            }
          },
          "metadata": {
            "useLiteralContent": true
          }
        }
      },
      "imports": [
        "./math/Math.sol",
        "./math/SignedMath.sol"
      ],
      "versionPragmas": [
        "^0.8.0"
      ],
      "artifacts": [
        "Strings"
      ]
    },
    "/Users/anjihwan/블벨/BusinessCard/contracts/utils/introspection/ERC165.sol": {
      "lastModificationDate": 1680085576152,
      "contentHash": "50942163b98dc94812317ecfddf42351",
      "sourceName": "contracts/utils/introspection/ERC165.sol",
      "solcConfig": {
        "version": "0.8.7",
        "settings": {
          "optimizer": {
            "enabled": false,
            "runs": 200
          },
          "outputSelection": {
            "*": {
              "*": [
                "abi",
                "evm.bytecode",
                "evm.deployedBytecode",
                "evm.methodIdentifiers",
                "metadata",
                "devdoc",
                "userdoc",
                "storageLayout",
                "evm.gasEstimates"
              ],
              "": [
                "ast"
              ]
            }
          },
          "metadata": {
            "useLiteralContent": true
          }
        }
      },
      "imports": [
        "./IERC165.sol"
      ],
      "versionPragmas": [
        "^0.8.0"
      ],
      "artifacts": [
        "ERC165"
      ]
    },
    "/Users/anjihwan/블벨/BusinessCard/contracts/utils/introspection/IERC165.sol": {
      "lastModificationDate": 1680085576153,
      "contentHash": "03e6768535ac4da0e9756f1d8a4a018a",
      "sourceName": "contracts/utils/introspection/IERC165.sol",
      "solcConfig": {
        "version": "0.8.7",
        "settings": {
          "optimizer": {
            "enabled": false,
            "runs": 200
          },
          "outputSelection": {
            "*": {
              "*": [
                "abi",
                "evm.bytecode",
                "evm.deployedBytecode",
                "evm.methodIdentifiers",
                "metadata",
                "devdoc",
                "userdoc",
                "storageLayout",
                "evm.gasEstimates"
              ],
              "": [
                "ast"
              ]
            }
          },
          "metadata": {
            "useLiteralContent": true
          }
        }
      },
      "imports": [],
      "versionPragmas": [
        "^0.8.0"
      ],
      "artifacts": [
        "IERC165"
      ]
    },
    "/Users/anjihwan/블벨/BusinessCard/contracts/utils/math/Math.sol": {
      "lastModificationDate": 1680085576154,
      "contentHash": "ff7fbb643fbd36e87b11890c1de9114b",
      "sourceName": "contracts/utils/math/Math.sol",
      "solcConfig": {
        "version": "0.8.7",
        "settings": {
          "optimizer": {
            "enabled": false,
            "runs": 200
          },
          "outputSelection": {
            "*": {
              "*": [
                "abi",
                "evm.bytecode",
                "evm.deployedBytecode",
                "evm.methodIdentifiers",
                "metadata",
                "devdoc",
                "userdoc",
                "storageLayout",
                "evm.gasEstimates"
              ],
              "": [
                "ast"
              ]
            }
          },
          "metadata": {
            "useLiteralContent": true
          }
        }
      },
      "imports": [],
      "versionPragmas": [
        "^0.8.0"
      ],
      "artifacts": [
        "Math"
      ]
    },
    "/Users/anjihwan/블벨/BusinessCard/contracts/utils/math/SignedMath.sol": {
      "lastModificationDate": 1680085576155,
      "contentHash": "9488ebd4daacfee8ad04811600d7d061",
      "sourceName": "contracts/utils/math/SignedMath.sol",
      "solcConfig": {
        "version": "0.8.7",
        "settings": {
          "optimizer": {
            "enabled": false,
            "runs": 200
          },
          "outputSelection": {
            "*": {
              "*": [
                "abi",
                "evm.bytecode",
                "evm.deployedBytecode",
                "evm.methodIdentifiers",
                "metadata",
                "devdoc",
                "userdoc",
                "storageLayout",
                "evm.gasEstimates"
              ],
              "": [
                "ast"
              ]
            }
          },
          "metadata": {
            "useLiteralContent": true
          }
        }
      },
      "imports": [],
      "versionPragmas": [
        "^0.8.0"
      ],
      "artifacts": [
        "SignedMath"
      ]
    },
    "/Users/anjihwan/블벨/BusinessCard/contracts/BCCoin.sol": {
      "lastModificationDate": 1680089273976,
      "contentHash": "a68f64ca95ea9a3d4084e96a89c6169c",
      "sourceName": "contracts/BCCoin.sol",
      "solcConfig": {
        "version": "0.8.7",
        "settings": {
          "optimizer": {
            "enabled": false,
            "runs": 200
          },
          "outputSelection": {
            "*": {
              "*": [
                "abi",
                "evm.bytecode",
                "evm.deployedBytecode",
                "evm.methodIdentifiers",
                "metadata",
                "devdoc",
                "userdoc",
                "storageLayout",
                "evm.gasEstimates"
              ],
              "": [
                "ast"
              ]
            }
          },
          "metadata": {
            "useLiteralContent": true
          }
        }
      },
      "imports": [
        "./ERC20.sol"
      ],
      "versionPragmas": [
        "^0.8.7"
      ],
      "artifacts": [
        "BCCoin"
      ]
    },
    "/Users/anjihwan/블벨/BusinessCard/contracts/ERC20.sol": {
      "lastModificationDate": 1680088994632,
      "contentHash": "f3f559135bf109fe7dda4127783d57cf",
      "sourceName": "contracts/ERC20.sol",
      "solcConfig": {
        "version": "0.8.7",
        "settings": {
          "optimizer": {
            "enabled": false,
            "runs": 200
          },
          "outputSelection": {
            "*": {
              "*": [
                "abi",
                "evm.bytecode",
                "evm.deployedBytecode",
                "evm.methodIdentifiers",
                "metadata",
                "devdoc",
                "userdoc",
                "storageLayout",
                "evm.gasEstimates"
              ],
              "": [
                "ast"
              ]
            }
          },
          "metadata": {
            "useLiteralContent": true
          }
        }
      },
      "imports": [
        "./IERC20.sol",
        "./extensions/IERC20Metadata.sol",
        "./utils/Context.sol"
      ],
      "versionPragmas": [
        "^0.8.0"
      ],
      "artifacts": [
        "ERC20"
      ]
    },
    "/Users/anjihwan/블벨/BusinessCard/contracts/IERC20.sol": {
      "lastModificationDate": 1680088944264,
      "contentHash": "d059f9e848b2658a0db2a702599bd65b",
      "sourceName": "contracts/IERC20.sol",
      "solcConfig": {
        "version": "0.8.7",
        "settings": {
          "optimizer": {
            "enabled": false,
            "runs": 200
          },
          "outputSelection": {
            "*": {
              "*": [
                "abi",
                "evm.bytecode",
                "evm.deployedBytecode",
                "evm.methodIdentifiers",
                "metadata",
                "devdoc",
                "userdoc",
                "storageLayout",
                "evm.gasEstimates"
              ],
              "": [
                "ast"
              ]
            }
          },
          "metadata": {
            "useLiteralContent": true
          }
        }
      },
      "imports": [],
      "versionPragmas": [
        "^0.8.0"
      ],
      "artifacts": [
        "IERC20"
      ]
    },
    "/Users/anjihwan/블벨/BusinessCard/contracts/extensions/IERC20Metadata.sol": {
      "lastModificationDate": 1680088990699,
      "contentHash": "909ab67fc5c25033fe6cd364f8c056f9",
      "sourceName": "contracts/extensions/IERC20Metadata.sol",
      "solcConfig": {
        "version": "0.8.7",
        "settings": {
          "optimizer": {
            "enabled": false,
            "runs": 200
          },
          "outputSelection": {
            "*": {
              "*": [
                "abi",
                "evm.bytecode",
                "evm.deployedBytecode",
                "evm.methodIdentifiers",
                "metadata",
                "devdoc",
                "userdoc",
                "storageLayout",
                "evm.gasEstimates"
              ],
              "": [
                "ast"
              ]
            }
          },
          "metadata": {
            "useLiteralContent": true
          }
        }
      },
      "imports": [
        "../IERC20.sol"
      ],
      "versionPragmas": [
        "^0.8.0"
      ],
      "artifacts": [
        "IERC20Metadata"
      ]
    },
    "/Users/anjihwan/블벨/BusinessCard/contracts/access/Ownable.sol": {
      "lastModificationDate": 1680089442910,
      "contentHash": "b49fa427e6e4677e567fecd397793dc3",
      "sourceName": "contracts/access/Ownable.sol",
      "solcConfig": {
        "version": "0.8.7",
        "settings": {
          "optimizer": {
            "enabled": false,
            "runs": 200
          },
          "outputSelection": {
            "*": {
              "*": [
                "abi",
                "evm.bytecode",
                "evm.deployedBytecode",
                "evm.methodIdentifiers",
                "metadata",
                "devdoc",
                "userdoc",
                "storageLayout",
                "evm.gasEstimates"
              ],
              "": [
                "ast"
              ]
            }
          },
          "metadata": {
            "useLiteralContent": true
          }
        }
      },
      "imports": [
        "../utils/Context.sol"
      ],
      "versionPragmas": [
        "^0.8.0"
      ],
      "artifacts": [
        "Ownable"
      ]
    },
    "/Users/anjihwan/블벨/BusinessCard/contracts/BusinessCardBase.sol": {
      "lastModificationDate": 1680161521746,
      "contentHash": "1d33c5215d6cf5b2d4049a1813297321",
      "sourceName": "contracts/BusinessCardBase.sol",
      "solcConfig": {
        "version": "0.8.7",
        "settings": {
          "optimizer": {
            "enabled": false,
            "runs": 200
          },
          "outputSelection": {
            "*": {
              "*": [
                "abi",
                "evm.bytecode",
                "evm.deployedBytecode",
                "evm.methodIdentifiers",
                "metadata",
                "devdoc",
                "userdoc",
                "storageLayout",
                "evm.gasEstimates"
              ],
              "": [
                "ast"
              ]
            }
          },
          "metadata": {
            "useLiteralContent": true
          }
        }
      },
      "imports": [
        "./ERC721EnumerableUpgradeable.sol",
        "./access/Ownable.sol"
      ],
      "versionPragmas": [
        "^0.8.7"
      ],
      "artifacts": [
        "BusinessCardBase"
      ]
    },
    "/Users/anjihwan/블벨/BusinessCard/contracts/ERC721EnumerableUpgradeable.sol": {
      "lastModificationDate": 1680097036987,
      "contentHash": "e86b26427f7818eb7140e6643aaccc73",
      "sourceName": "contracts/ERC721EnumerableUpgradeable.sol",
      "solcConfig": {
        "version": "0.8.7",
        "settings": {
          "optimizer": {
            "enabled": false,
            "runs": 200
          },
          "outputSelection": {
            "*": {
              "*": [
                "abi",
                "evm.bytecode",
                "evm.deployedBytecode",
                "evm.methodIdentifiers",
                "metadata",
                "devdoc",
                "userdoc",
                "storageLayout",
                "evm.gasEstimates"
              ],
              "": [
                "ast"
              ]
            }
          },
          "metadata": {
            "useLiteralContent": true
          }
        }
      },
      "imports": [
        "./ERC721Upgradeable.sol",
        "./IERC721EnumerableUpgradeable.sol",
        "./proxy/utils/Initializable.sol"
      ],
      "versionPragmas": [
        "^0.8.0"
      ],
      "artifacts": [
        "ERC721EnumerableUpgradeable"
      ]
    },
    "/Users/anjihwan/블벨/BusinessCard/contracts/ERC721Upgradeable.sol": {
      "lastModificationDate": 1680098553300,
      "contentHash": "74bcd5dfda10e5b5592b543a7a3997cf",
      "sourceName": "contracts/ERC721Upgradeable.sol",
      "solcConfig": {
        "version": "0.8.7",
        "settings": {
          "optimizer": {
            "enabled": false,
            "runs": 200
          },
          "outputSelection": {
            "*": {
              "*": [
                "abi",
                "evm.bytecode",
                "evm.deployedBytecode",
                "evm.methodIdentifiers",
                "metadata",
                "devdoc",
                "userdoc",
                "storageLayout",
                "evm.gasEstimates"
              ],
              "": [
                "ast"
              ]
            }
          },
          "metadata": {
            "useLiteralContent": true
          }
        }
      },
      "imports": [
        "./IERC721Upgradeable.sol",
        "./IERC721ReceiverUpgradeable.sol",
        "./extensions/IERC721MetadataUpgradeable.sol",
        "./utils/AddressUpgradeable.sol",
        "./utils/ContextUpgradeable.sol",
        "./utils/StringsUpgradeable.sol",
        "./utils/introspection/ERC165Upgradeable.sol",
        "./proxy/utils/Initializable.sol"
      ],
      "versionPragmas": [
        "^0.8.0"
      ],
      "artifacts": [
        "ERC721Upgradeable"
      ]
    },
    "/Users/anjihwan/블벨/BusinessCard/contracts/proxy/utils/Initializable.sol": {
      "lastModificationDate": 1680096897536,
      "contentHash": "67e0769cd994c90535aedb500d4b7d9c",
      "sourceName": "contracts/proxy/utils/Initializable.sol",
      "solcConfig": {
        "version": "0.8.7",
        "settings": {
          "optimizer": {
            "enabled": false,
            "runs": 200
          },
          "outputSelection": {
            "*": {
              "*": [
                "abi",
                "evm.bytecode",
                "evm.deployedBytecode",
                "evm.methodIdentifiers",
                "metadata",
                "devdoc",
                "userdoc",
                "storageLayout",
                "evm.gasEstimates"
              ],
              "": [
                "ast"
              ]
            }
          },
          "metadata": {
            "useLiteralContent": true
          }
        }
      },
      "imports": [
        "../../utils/AddressUpgradeable.sol"
      ],
      "versionPragmas": [
        "^0.8.2"
      ],
      "artifacts": [
        "Initializable"
      ]
    },
    "/Users/anjihwan/블벨/BusinessCard/contracts/IERC721EnumerableUpgradeable.sol": {
      "lastModificationDate": 1680097097930,
      "contentHash": "793b11221d3bce38dc12cd33fc7b46a8",
      "sourceName": "contracts/IERC721EnumerableUpgradeable.sol",
      "solcConfig": {
        "version": "0.8.7",
        "settings": {
          "optimizer": {
            "enabled": false,
            "runs": 200
          },
          "outputSelection": {
            "*": {
              "*": [
                "abi",
                "evm.bytecode",
                "evm.deployedBytecode",
                "evm.methodIdentifiers",
                "metadata",
                "devdoc",
                "userdoc",
                "storageLayout",
                "evm.gasEstimates"
              ],
              "": [
                "ast"
              ]
            }
          },
          "metadata": {
            "useLiteralContent": true
          }
        }
      },
      "imports": [
        "./IERC721Upgradeable.sol"
      ],
      "versionPragmas": [
        "^0.8.0"
      ],
      "artifacts": [
        "IERC721EnumerableUpgradeable"
      ]
    },
    "/Users/anjihwan/블벨/BusinessCard/contracts/IERC721ReceiverUpgradeable.sol": {
      "lastModificationDate": 1680098007040,
      "contentHash": "ba28cf60b52b00d2b3a190bcdf0952bd",
      "sourceName": "contracts/IERC721ReceiverUpgradeable.sol",
      "solcConfig": {
        "version": "0.8.7",
        "settings": {
          "optimizer": {
            "enabled": false,
            "runs": 200
          },
          "outputSelection": {
            "*": {
              "*": [
                "abi",
                "evm.bytecode",
                "evm.deployedBytecode",
                "evm.methodIdentifiers",
                "metadata",
                "devdoc",
                "userdoc",
                "storageLayout",
                "evm.gasEstimates"
              ],
              "": [
                "ast"
              ]
            }
          },
          "metadata": {
            "useLiteralContent": true
          }
        }
      },
      "imports": [],
      "versionPragmas": [
        "^0.8.0"
      ],
      "artifacts": [
        "IERC721ReceiverUpgradeable"
      ]
    },
    "/Users/anjihwan/블벨/BusinessCard/contracts/extensions/IERC721MetadataUpgradeable.sol": {
      "lastModificationDate": 1680098135807,
      "contentHash": "76212ca0265501d1eb3dd1175e6afca4",
      "sourceName": "contracts/extensions/IERC721MetadataUpgradeable.sol",
      "solcConfig": {
        "version": "0.8.7",
        "settings": {
          "optimizer": {
            "enabled": false,
            "runs": 200
          },
          "outputSelection": {
            "*": {
              "*": [
                "abi",
                "evm.bytecode",
                "evm.deployedBytecode",
                "evm.methodIdentifiers",
                "metadata",
                "devdoc",
                "userdoc",
                "storageLayout",
                "evm.gasEstimates"
              ],
              "": [
                "ast"
              ]
            }
          },
          "metadata": {
            "useLiteralContent": true
          }
        }
      },
      "imports": [
        "../IERC721Upgradeable.sol"
      ],
      "versionPragmas": [
        "^0.8.0"
      ],
      "artifacts": [
        "IERC721MetadataUpgradeable"
      ]
    },
    "/Users/anjihwan/블벨/BusinessCard/contracts/utils/AddressUpgradeable.sol": {
      "lastModificationDate": 1680096894642,
      "contentHash": "c673be135a07b13f3768b249c0574d60",
      "sourceName": "contracts/utils/AddressUpgradeable.sol",
      "solcConfig": {
        "version": "0.8.7",
        "settings": {
          "optimizer": {
            "enabled": false,
            "runs": 200
          },
          "outputSelection": {
            "*": {
              "*": [
                "abi",
                "evm.bytecode",
                "evm.deployedBytecode",
                "evm.methodIdentifiers",
                "metadata",
                "devdoc",
                "userdoc",
                "storageLayout",
                "evm.gasEstimates"
              ],
              "": [
                "ast"
              ]
            }
          },
          "metadata": {
            "useLiteralContent": true
          }
        }
      },
      "imports": [],
      "versionPragmas": [
        "^0.8.1"
      ],
      "artifacts": [
        "AddressUpgradeable"
      ]
    },
    "/Users/anjihwan/블벨/BusinessCard/contracts/utils/ContextUpgradeable.sol": {
      "lastModificationDate": 1680098534743,
      "contentHash": "ede4805287e93d646247d407cfbba534",
      "sourceName": "contracts/utils/ContextUpgradeable.sol",
      "solcConfig": {
        "version": "0.8.7",
        "settings": {
          "optimizer": {
            "enabled": false,
            "runs": 200
          },
          "outputSelection": {
            "*": {
              "*": [
                "abi",
                "evm.bytecode",
                "evm.deployedBytecode",
                "evm.methodIdentifiers",
                "metadata",
                "devdoc",
                "userdoc",
                "storageLayout",
                "evm.gasEstimates"
              ],
              "": [
                "ast"
              ]
            }
          },
          "metadata": {
            "useLiteralContent": true
          }
        }
      },
      "imports": [
        "../proxy/utils/Initializable.sol"
      ],
      "versionPragmas": [
        "^0.8.0"
      ],
      "artifacts": [
        "ContextUpgradeable"
      ]
    },
    "/Users/anjihwan/블벨/BusinessCard/contracts/IERC721Upgradeable.sol": {
      "lastModificationDate": 1680097182314,
      "contentHash": "b1b1428a1161c9cd9086f767ec613dcf",
      "sourceName": "contracts/IERC721Upgradeable.sol",
      "solcConfig": {
        "version": "0.8.7",
        "settings": {
          "optimizer": {
            "enabled": false,
            "runs": 200
          },
          "outputSelection": {
            "*": {
              "*": [
                "abi",
                "evm.bytecode",
                "evm.deployedBytecode",
                "evm.methodIdentifiers",
                "metadata",
                "devdoc",
                "userdoc",
                "storageLayout",
                "evm.gasEstimates"
              ],
              "": [
                "ast"
              ]
            }
          },
          "metadata": {
            "useLiteralContent": true
          }
        }
      },
      "imports": [
        "./utils/introspection/IERC165Upgradeable.sol"
      ],
      "versionPragmas": [
        "^0.8.0"
      ],
      "artifacts": [
        "IERC721Upgradeable"
      ]
    },
    "/Users/anjihwan/블벨/BusinessCard/contracts/utils/StringsUpgradeable.sol": {
      "lastModificationDate": 1680098038874,
      "contentHash": "1b47e3c448008f7b0336c1ad68ac4a8d",
      "sourceName": "contracts/utils/StringsUpgradeable.sol",
      "solcConfig": {
        "version": "0.8.7",
        "settings": {
          "optimizer": {
            "enabled": false,
            "runs": 200
          },
          "outputSelection": {
            "*": {
              "*": [
                "abi",
                "evm.bytecode",
                "evm.deployedBytecode",
                "evm.methodIdentifiers",
                "metadata",
                "devdoc",
                "userdoc",
                "storageLayout",
                "evm.gasEstimates"
              ],
              "": [
                "ast"
              ]
            }
          },
          "metadata": {
            "useLiteralContent": true
          }
        }
      },
      "imports": [
        "./math/MathUpgradeable.sol",
        "./math/SignedMathUpgradeable.sol"
      ],
      "versionPragmas": [
        "^0.8.0"
      ],
      "artifacts": [
        "StringsUpgradeable"
      ]
    },
    "/Users/anjihwan/블벨/BusinessCard/contracts/utils/introspection/ERC165Upgradeable.sol": {
      "lastModificationDate": 1680098451027,
      "contentHash": "162d6e5ab1c88d03fd7e70827cd00522",
      "sourceName": "contracts/utils/introspection/ERC165Upgradeable.sol",
      "solcConfig": {
        "version": "0.8.7",
        "settings": {
          "optimizer": {
            "enabled": false,
            "runs": 200
          },
          "outputSelection": {
            "*": {
              "*": [
                "abi",
                "evm.bytecode",
                "evm.deployedBytecode",
                "evm.methodIdentifiers",
                "metadata",
                "devdoc",
                "userdoc",
                "storageLayout",
                "evm.gasEstimates"
              ],
              "": [
                "ast"
              ]
            }
          },
          "metadata": {
            "useLiteralContent": true
          }
        }
      },
      "imports": [
        "./IERC165Upgradeable.sol",
        "../../proxy/utils/Initializable.sol"
      ],
      "versionPragmas": [
        "^0.8.0"
      ],
      "artifacts": [
        "ERC165Upgradeable"
      ]
    },
    "/Users/anjihwan/블벨/BusinessCard/contracts/utils/introspection/IERC165Upgradeable.sol": {
      "lastModificationDate": 1680097169188,
      "contentHash": "d6ecf203a5e72c845be9bbf2f304a289",
      "sourceName": "contracts/utils/introspection/IERC165Upgradeable.sol",
      "solcConfig": {
        "version": "0.8.7",
        "settings": {
          "optimizer": {
            "enabled": false,
            "runs": 200
          },
          "outputSelection": {
            "*": {
              "*": [
                "abi",
                "evm.bytecode",
                "evm.deployedBytecode",
                "evm.methodIdentifiers",
                "metadata",
                "devdoc",
                "userdoc",
                "storageLayout",
                "evm.gasEstimates"
              ],
              "": [
                "ast"
              ]
            }
          },
          "metadata": {
            "useLiteralContent": true
          }
        }
      },
      "imports": [],
      "versionPragmas": [
        "^0.8.0"
      ],
      "artifacts": [
        "IERC165Upgradeable"
      ]
    },
    "/Users/anjihwan/블벨/BusinessCard/contracts/utils/math/MathUpgradeable.sol": {
      "lastModificationDate": 1680098062105,
      "contentHash": "47d6c3925ca95e875a0131055a631fe8",
      "sourceName": "contracts/utils/math/MathUpgradeable.sol",
      "solcConfig": {
        "version": "0.8.7",
        "settings": {
          "optimizer": {
            "enabled": false,
            "runs": 200
          },
          "outputSelection": {
            "*": {
              "*": [
                "abi",
                "evm.bytecode",
                "evm.deployedBytecode",
                "evm.methodIdentifiers",
                "metadata",
                "devdoc",
                "userdoc",
                "storageLayout",
                "evm.gasEstimates"
              ],
              "": [
                "ast"
              ]
            }
          },
          "metadata": {
            "useLiteralContent": true
          }
        }
      },
      "imports": [],
      "versionPragmas": [
        "^0.8.0"
      ],
      "artifacts": [
        "MathUpgradeable"
      ]
    },
    "/Users/anjihwan/블벨/BusinessCard/contracts/utils/math/SignedMathUpgradeable.sol": {
      "lastModificationDate": 1680098082578,
      "contentHash": "2a6b819b2e241091ada6d645df3e3929",
      "sourceName": "contracts/utils/math/SignedMathUpgradeable.sol",
      "solcConfig": {
        "version": "0.8.7",
        "settings": {
          "optimizer": {
            "enabled": false,
            "runs": 200
          },
          "outputSelection": {
            "*": {
              "*": [
                "abi",
                "evm.bytecode",
                "evm.deployedBytecode",
                "evm.methodIdentifiers",
                "metadata",
                "devdoc",
                "userdoc",
                "storageLayout",
                "evm.gasEstimates"
              ],
              "": [
                "ast"
              ]
            }
          },
          "metadata": {
            "useLiteralContent": true
          }
        }
      },
      "imports": [],
      "versionPragmas": [
        "^0.8.0"
      ],
      "artifacts": [
        "SignedMathUpgradeable"
      ]
    },
    "/Users/anjihwan/블벨/BusinessCard/contracts/BusinessCardMarketplace.sol": {
      "lastModificationDate": 1680151841734,
      "contentHash": "ae166086bf906b4a7a4a9e1a085abe98",
      "sourceName": "contracts/BusinessCardMarketplace.sol",
      "solcConfig": {
        "version": "0.8.7",
        "settings": {
          "optimizer": {
            "enabled": false,
            "runs": 200
          },
          "outputSelection": {
            "*": {
              "*": [
                "abi",
                "evm.bytecode",
                "evm.deployedBytecode",
                "evm.methodIdentifiers",
                "metadata",
                "devdoc",
                "userdoc",
                "storageLayout",
                "evm.gasEstimates"
              ],
              "": [
                "ast"
              ]
            }
          },
          "metadata": {
            "useLiteralContent": true
          }
        }
      },
      "imports": [
        "./IERC721.sol"
      ],
      "versionPragmas": [
        "^0.8.7"
      ],
      "artifacts": [
        "BusinessCardMarketplace"
      ]
    }
  }
}
